bank_app/__init__.py
bank_app/__main__.py
bank_app/cli.py
bank_app/core.py
dio_bank_app-3.0.0.dist-info/METADATA
dio_bank_app-3.0.0.dist-info/WHEEL
dio_bank_app-3.0.0.dist-info/entry_points.txt
dio_bank_app-3.0.0.dist-info/top_level.txt
dio_bank_app-3.0.0.dist-info/RECORD
