Metadata-Version: 2.4
Name: dio-bank-app
Version: 3.0.0
Summary: Aplicativo bancário em Python (CLI), evoluindo desde v1 até v3 (POO), com múltiplos usuários, contas e persistência em JSON.
Author: Padula, Diego A.
License: MIT
Project-URL: Homepage, https://github.com/paduladiego/DIO_bank_app
Project-URL: Source, https://github.com/paduladiego/DIO_bank_app/issues
Keywords: bank,cli,dio,educational,finances,Suzano
Classifier: Programming Language :: Python :: 3
Classifier: Programming Language :: Python :: 3.10
Classifier: Programming Language :: Python :: 3.11
Classifier: Programming Language :: Python :: 3.12
Classifier: License :: OSI Approved :: MIT License
Classifier: Environment :: Console
Classifier: Intended Audience :: Education
Classifier: Topic :: Office/Business :: Financial
Requires-Python: >=3.10
